{
    "titles" : {
        "contact" : { "en" : "Contact Info:", "es" : "Información de contácto:" },
        "profile" : { "en" : "Profile", "es" : "Perfil:" },
        "experience" : { "en" : "Experience:", "es" : "Experiencia:" },
        "skills" : { "en" : "Skills:", "es" : "Habilidades:" },
        "education" : { "en" : "Education:", "es" : "Educación:" }
    },
    "labels": {
        "phone": { "en": "Phone:", "es": "Teléfono:" },
        "email": { "en": "Email:", "es": "Correo electrónico:" },
        "address": { "en": "Address:", "es": "Dirección:" },
        "skills": { "en": "Skills:", "es": "Habilidades:" },
        "profile": { "en": "Profile:", "es": "Perfil:" },
        "experience": { "en": "Experience:", "es": "Experiencia:" },
        "education": { "en": "Education:", "es": "Educación:" }
    }
}
